father_humor_pip_package/__init__.py
father_humor_pip_package/scraper.py
father_humor_pip_package/.pytest_cache/.gitignore
father_humor_pip_package/.pytest_cache/CACHEDIR.TAG
father_humor_pip_package/.pytest_cache/README.md
father_humor_pip_package/.pytest_cache/v/cache/nodeids
father_humor_pip_package/.pytest_cache/v/cache/stepwise
father_humor_pip_package-2.0.1.dist-info/METADATA
father_humor_pip_package-2.0.1.dist-info/WHEEL
father_humor_pip_package-2.0.1.dist-info/licenses/LICENSE
father_humor_pip_package-2.0.1.dist-info/RECORD
