Metadata-Version: 2.1
Name: father_humor_pip_package
Version: 2.0.1
Summary: father-humor is a PIP package that you can install to utilize the built-in import method and render dad jokes directly to your terminal or your project's front-end deployment.
Project-URL: Homepage, https://github.com/TheYoungAndTheRESTless/father_humor
Project-URL: Bug Tracker, https://github.com/orgs/TheYoungAndTheRESTless/projects/1/views/1
Author-email: Anthony Hill <anthonyhilldeveloper@gmail.com>, Brian Tarte <brianjtarte@gmail.com>, Ibraheem Ibraheem <iibraheem2001@gmail.com>, Brendon Hampton <brendonhampton1988@gmail.com>
License: Copyright (c) 2018 The Python Packaging Authority
Classifier: License :: OSI Approved :: MIT License
Classifier: Operating System :: OS Independent
Classifier: Programming Language :: Python :: 3
Requires-Python: >=3.7
